adilsm/__init__.py
adilsm/adilsm.py
adilsm-0.0.12.dist-info/LICENSE
adilsm-0.0.12.dist-info/METADATA
adilsm-0.0.12.dist-info/WHEEL
adilsm-0.0.12.dist-info/top_level.txt
adilsm-0.0.12.dist-info/RECORD
