Metadata-Version: 2.1
Name: adilsm
Version: 0.0.12
Summary: Integrated Latent Multi Source Model
Home-page: https://github.com/Advestis/adilsm
Author: Mazars
Author-email: victor.chemla@mazars.fr
License: MIT
Project-URL: Bug Tracker, https://github.com/Advestis/adilsm/issues
Project-URL: Documentation, https://advestis.github.io/adilsm
Project-URL: Source Code, https://github.com/Advestis/adilsm/
Classifier: Development Status :: 5 - Production/Stable
Classifier: License :: OSI Approved :: MIT License
Classifier: Operating System :: Unix
Classifier: Operating System :: Microsoft :: Windows
Classifier: Programming Language :: Python :: 3.9
Classifier: Programming Language :: Python :: 3.10
Requires-Python: >=3.9
License-File: LICENSE
Requires-Dist: adnmtf ==0.1.164
Requires-Dist: scipy ==1.9.1
